titok_pytorch/__init__.py
titok_pytorch/titok.py
titok_pytorch-0.0.5.dist-info/METADATA
titok_pytorch-0.0.5.dist-info/WHEEL
titok_pytorch-0.0.5.dist-info/licenses/LICENSE
titok_pytorch-0.0.5.dist-info/RECORD
