Metadata-Version: 2.3
Name: titok-pytorch
Version: 0.0.5
Summary: TiTok - Pytorch
Project-URL: Homepage, https://pypi.org/project/titok-pytorch/
Project-URL: Repository, https://github.com/lucidrains/titok-pytorch
Author-email: Phil Wang <lucidrains@gmail.com>
License: MIT License
License-File: LICENSE
Keywords: artificial intelligence,deep learning,image compression,image generation,vector quantization
Classifier: Development Status :: 4 - Beta
Classifier: Intended Audience :: Developers
Classifier: License :: OSI Approved :: MIT License
Classifier: Programming Language :: Python :: 3.9
Classifier: Topic :: Scientific/Engineering :: Artificial Intelligence
Requires-Python: >=3.9
Requires-Dist: einops>=0.8.0
Requires-Dist: torch>=2.0
Requires-Dist: vector-quantize-pytorch>=1.14.26
Requires-Dist: x-transformers>=1.30.20
Provides-Extra: examples
Provides-Extra: test
Requires-Dist: pytest; extra == 'test'
